{"metadata":{"dist-tags":{"version-2":"2.6.21","latest":"3.2.3"},"versions":{"1.0.0":{"name":"csstype","dist":{"tarball":"https://registry.npmjs.org/csstype/-/csstype-1.0.0.tgz"},"scripts":{"test":"jest","build":"ts-node build.ts","watch":"ts-node build.ts --watch","prettier":"prettier --single-quote --write build.ts */*.ts","prepublish":"npm run test && npm run build"}},"1.0.1":{"name":"csstype","dist":{"tarball":"https://registry.npmjs.org/csstype/-/csstype-1.0.1.tgz"},"scripts":{"test":"jest","build":"ts-node build.ts","watch":"ts-node build.ts --watch","prettier":"prettier --single-quote --write build.ts */*.ts","prepublish":"npm run test && npm run build"}},"1.1.0":{"name":"csstype","dist":{"tarball":"https://registry.npmjs.org/csstype/-/csstype-1.1.0.tgz"},"scripts":{"test":"jest","build":"ts-node build.ts","watch":"ts-node build.ts --watch","prettier":"prettier --single-quote --write build.ts */*.ts","prepublish":"npm run test && npm run build"}},"1.2.0":{"name":"csstype","dist":{"tarball":"https://registry.npmjs.org/csstype/-/csstype-1.2.0.tgz"},"scripts":{"test":"jest","build":"ts-node build.ts","watch":"ts-node build.ts --watch","prettier":"prettier --single-quote --write build.ts */*.ts","prepublish":"npm run test && npm run build"}},"1.2.1":{"name":"csstype","dist":{"tarball":"https://registry.npmjs.org/csstype/-/csstype-1.2.1.tgz"},"scripts":{"test":"jest --no-cache","build":"ts-node build.ts","watch":"ts-node build.ts --watch","pretty":"prettier --single-quote --write build.ts **/*.ts","prepare":"tsc && npm run test && npm run build"}},"1.3.0":{"name":"csstype","dist":{"tarball":"https://registry.npmjs.org/csstype/-/csstype-1.3.0.tgz"},"scripts":{"test":"jest --no-cache","build":"ts-node build.ts","watch":"ts-node build.ts --watch","pretty":"prettier --single-quote --write build.ts **/*.ts","prepare":"npm run test && npm run build && tsc typecheck.ts --noEmit"}},"1.4.0":{"name":"csstype","dist":{"tarball":"https://registry.npmjs.org/csstype/-/csstype-1.4.0.tgz"},"scripts":{"test":"jest --no-cache","build":"ts-node build.ts","watch":"ts-node build.ts --watch","pretty":"prettier --write build.ts **/*.{ts,js,json}","prepublish":"tsc && npm run test && npm run build && tsc typecheck.ts --noEmit"}},"1.5.0":{"name":"csstype","dist":{"tarball":"https://registry.npmjs.org/csstype/-/csstype-1.5.0.tgz"},"scripts":{"lint":"tslint --exclude node_modules/**/* --exclude **/*.d.ts --fix **/*.ts","test":"jest --no-cache","build":"ts-node build.ts","watch":"ts-node build.ts --watch","pretty":"prettier --write build.ts **/*.{ts,js,json}","sloppy":"tsc && npm run lint && npm run pretty","prepublish":"tsc && npm run test && npm run build && tsc typecheck.ts --noEmit"}},"1.6.0":{"name":"csstype","dist":{"tarball":"https://registry.npmjs.org/csstype/-/csstype-1.6.0.tgz"},"scripts":{"lint":"tslint --exclude node_modules/**/* --exclude **/*.d.ts --fix **/*.ts","test":"jest --no-cache","build":"ts-node build.ts","watch":"ts-node build.ts --watch","pretty":"prettier --write build.ts **/*.{ts,js,json}","sloppy":"tsc && npm run lint && npm run pretty","prepublish":"tsc && npm run test && npm run build && tsc typecheck.ts --noEmit"}},"1.7.0":{"name":"csstype","dist":{"tarball":"https://registry.npmjs.org/csstype/-/csstype-1.7.0.tgz"},"scripts":{"lint":"tslint --exclude node_modules/**/* --exclude **/*.d.ts --fix **/*.ts","test":"jest --no-cache","build":"ts-node build.ts","watch":"ts-node build.ts --watch","pretty":"prettier --write build.ts **/*.{ts,js,json}","sloppy":"tsc && npm run lint && npm run pretty","prepublish":"tsc && npm run test && npm run build && tsc typecheck.ts --noEmit"}},"1.7.1":{"name":"csstype","dist":{"tarball":"https://registry.npmjs.org/csstype/-/csstype-1.7.1.tgz"},"scripts":{"lazy":"tsc && npm run lint && npm run pretty","lint":"tslint --exclude node_modules/**/* --exclude **/*.d.ts --fix **/*.ts","test":"jest --no-cache","build":"ts-node build.ts","watch":"ts-node build.ts --watch","pretty":"prettier --write build.ts **/*.{ts,js,json}","prepublish":"tsc && npm run test && npm run build && tsc typecheck.ts --noEmit"}},"1.7.2":{"name":"csstype","dist":{"tarball":"https://registry.npmjs.org/csstype/-/csstype-1.7.2.tgz"},"scripts":{"lazy":"tsc && npm run lint && npm run pretty","lint":"tslint --exclude node_modules/**/* --exclude **/*.d.ts --fix **/*.ts","test":"jest --no-cache","build":"ts-node build.ts","watch":"ts-node build.ts --watch","pretty":"prettier --write build.ts **/*.{ts,js,json}","prepublish":"tsc && npm run test && npm run build && tsc typecheck.ts --noEmit"}},"1.8.0":{"name":"csstype","dist":{"tarball":"https://registry.npmjs.org/csstype/-/csstype-1.8.0.tgz"},"scripts":{"lazy":"tsc && npm run lint && npm run pretty","lint":"tslint --exclude node_modules/**/* --exclude **/*.d.ts --fix **/*.ts","test":"jest --no-cache","build":"ts-node build.ts","watch":"ts-node build.ts --watch","pretty":"prettier --write build.ts **/*.{ts,js,json}","typecheck":"tsc typecheck.ts --noEmit --pretty & flow check typecheck.js","prepublish":"tsc && npm run test && npm run build && npm run typecheck"}},"1.8.1":{"name":"csstype","dist":{"tarball":"https://registry.npmjs.org/csstype/-/csstype-1.8.1.tgz"},"scripts":{"lazy":"tsc && npm run lint && npm run pretty","lint":"tslint --exclude node_modules/**/* --exclude **/*.d.ts --fix **/*.ts","test":"jest --no-cache","build":"ts-node build.ts","watch":"ts-node build.ts --watch","pretty":"prettier --write build.ts **/*.{ts,js,json}","typecheck":"tsc typecheck.ts --noEmit --pretty & flow check typecheck.js","prepublish":"tsc && npm run test && npm run build && npm run typecheck"}},"1.8.2":{"name":"csstype","dist":{"tarball":"https://registry.npmjs.org/csstype/-/csstype-1.8.2.tgz"},"scripts":{"lazy":"tsc && npm run lint && npm run pretty","lint":"tslint --exclude node_modules/**/* --exclude **/*.d.ts --fix **/*.ts","test":"jest --no-cache","build":"ts-node build.ts","watch":"ts-node build.ts --watch","pretty":"prettier --write build.ts **/*.{ts,js,json}","typecheck":"tsc typecheck.ts --noEmit --pretty & flow check typecheck.js","prepublish":"tsc && npm run test && npm run build && npm run typecheck"}},"2.0.0":{"name":"csstype","dist":{"tarball":"https://registry.npmjs.org/csstype/-/csstype-2.0.0.tgz"},"scripts":{"lazy":"tsc && npm run lint && npm run pretty","lint":"tslint --exclude node_modules/**/* --exclude **/*.d.ts --fix **/*.ts","test":"jest --no-cache","build":"ts-node build.ts","watch":"ts-node build.ts --watch","pretty":"prettier --write build.ts **/*.{ts,js,json}","typecheck":"tsc typecheck.ts --noEmit --pretty & flow check typecheck.js","prepublish":"tsc && npm run test && npm run build && npm run typecheck"}},"2.1.0":{"name":"csstype","dist":{"tarball":"https://registry.npmjs.org/csstype/-/csstype-2.1.0.tgz"},"scripts":{"lazy":"tsc && npm run lint && npm run pretty","lint":"tslint --exclude node_modules/**/* --exclude **/*.d.ts --fix **/*.ts","test":"jest --no-cache","build":"ts-node build.ts","watch":"ts-node build.ts --watch","pretty":"prettier --write build.ts **/*.{ts,js,json}","typecheck":"tsc typecheck.ts --noEmit --pretty & flow check typecheck.js","prepublish":"tsc && npm run test && npm run build && npm run typecheck"}},"2.1.1":{"name":"csstype","dist":{"tarball":"https://registry.npmjs.org/csstype/-/csstype-2.1.1.tgz"},"scripts":{"lazy":"tsc && npm run lint && npm run pretty","lint":"tslint --exclude node_modules/**/* --exclude **/*.d.ts --fix **/*.ts","test":"jest --no-cache","build":"ts-node build.ts","watch":"ts-node build.ts --watch","pretty":"prettier --write build.ts **/*.{ts,js,json}","typecheck":"tsc typecheck.ts --noEmit --pretty & flow check typecheck.js","prepublish":"tsc && npm run test && npm run build && npm run typecheck"}},"2.2.0":{"name":"csstype","dist":{"tarball":"https://registry.npmjs.org/csstype/-/csstype-2.2.0.tgz"},"scripts":{"lazy":"tsc && npm run lint && npm run pretty","lint":"tslint --exclude node_modules/**/* --exclude **/*.d.ts --fix **/*.ts","test":"jest --no-cache","build":"ts-node build.ts","watch":"ts-node build.ts --watch","pretty":"prettier --write build.ts **/*.{ts,js,json}","typecheck":"tsc typecheck.ts --noEmit --pretty & flow check typecheck.js","prepublish":"tsc && npm run test && npm run build && npm run typecheck","rebase-build":"git rebase -s recursive -X theirs --exec \"yarn build && git commit -a --amend --no-verify --no-edit --allow-empty\""}},"2.3.0":{"name":"csstype","dist":{"tarball":"https://registry.npmjs.org/csstype/-/csstype-2.3.0.tgz"},"scripts":{"lazy":"tsc && npm run lint && npm run pretty","lint":"tslint --exclude node_modules/**/* --exclude **/*.d.ts --fix **/*.ts","test":"jest --no-cache","build":"ts-node build.ts","watch":"ts-node build.ts --watch","pretty":"prettier --write build.ts **/*.{ts,js,json}","typecheck":"tsc typecheck.ts --noEmit --pretty & flow check typecheck.js","prepublish":"tsc && npm run test && npm run build && npm run typecheck","rebase-build":"git rebase --exec \"yarn --ignore-scripts && yarn build && git commit -a --amend --no-verify --no-edit --allow-empty\""}},"2.3.1":{"name":"csstype","dist":{"tarball":"https://registry.npmjs.org/csstype/-/csstype-2.3.1.tgz"},"scripts":{"lazy":"tsc && npm run lint && npm run pretty","lint":"tslint --exclude node_modules/**/* --exclude **/*.d.ts --fix **/*.ts","test":"jest --no-cache","build":"ts-node build.ts","watch":"ts-node build.ts --watch","pretty":"prettier --write build.ts **/*.{ts,js,json}","typecheck":"tsc typecheck.ts --noEmit --pretty & flow check typecheck.js","prepublish":"tsc && npm run test && npm run build && npm run typecheck","rebase-build":"git rebase --exec \"yarn --ignore-scripts && yarn build && git commit -a --amend --no-verify --no-edit --allow-empty\""}},"2.4.0":{"name":"csstype","dist":{"tarball":"https://registry.npmjs.org/csstype/-/csstype-2.4.0.tgz"},"scripts":{"lazy":"tsc && npm run lint && npm run pretty","lint":"tslint --exclude node_modules/**/* --exclude **/*.d.ts --fix **/*.ts","test":"jest --no-cache","build":"ts-node build.ts","watch":"ts-node build.ts --watch","pretty":"prettier --write build.ts **/*.{ts,js,json}","typecheck":"tsc typecheck.ts --noEmit --pretty & flow check typecheck.js","prepublish":"tsc && npm run test && npm run build && npm run typecheck","rebase-build":"git rebase --exec \"yarn --ignore-scripts && yarn build && git commit -a --amend --no-verify --no-edit --allow-empty\""}},"2.4.1":{"name":"csstype","dist":{"tarball":"https://registry.npmjs.org/csstype/-/csstype-2.4.1.tgz"},"scripts":{"lazy":"tsc && npm run lint && npm run pretty","lint":"tslint --exclude node_modules/**/* --exclude **/*.d.ts --fix **/*.ts","test":"jest --no-cache","build":"ts-node build.ts","watch":"ts-node build.ts --watch","pretty":"prettier --write build.ts **/*.{ts,js,json}","typecheck":"tsc typecheck.ts --noEmit --pretty & flow check typecheck.js","prepublish":"tsc && npm run test && npm run build && npm run typecheck","rebase-build":"git rebase --exec \"yarn --ignore-scripts && yarn build && git commit -a --amend --no-verify --no-edit --allow-empty\""}},"2.4.2":{"name":"csstype","dist":{"tarball":"https://registry.npmjs.org/csstype/-/csstype-2.4.2.tgz"},"scripts":{"lazy":"tsc && npm run lint && npm run pretty","lint":"tslint --exclude node_modules/**/* --exclude **/*.d.ts --fix **/*.ts","test":"jest --no-cache","build":"ts-node build.ts --start","watch":"ts-node build.ts --watch","pretty":"prettier --write build.ts **/*.{ts,js,json}","update":"ts-node update.ts","typecheck":"tsc typecheck.ts --noEmit --pretty & flow check typecheck.js","prepublish":"tsc && npm run test && npm run build && npm run typecheck","rebase-build":"git rebase --exec \"yarn --ignore-scripts && yarn build && git commit -a --amend --no-verify --no-edit --allow-empty\""}},"2.5.0":{"name":"csstype","dist":{"tarball":"https://registry.npmjs.org/csstype/-/csstype-2.5.0.tgz"},"scripts":{"lazy":"tsc && npm run lint && npm run pretty","lint":"tslint --exclude node_modules/**/* --exclude **/*.d.ts --fix **/*.ts","test":"jest --no-cache","build":"ts-node build.ts --start","watch":"ts-node build.ts --watch","pretty":"prettier --write build.ts **/*.{ts,js,json}","update":"ts-node update.ts","typecheck":"tsc typecheck.ts --noEmit --pretty & flow check typecheck.js","prepublish":"tsc && npm run test && npm run build && npm run typecheck","rebase-build":"git rebase --exec \"yarn --ignore-scripts && yarn build && git commit -a --amend --no-verify --no-edit --allow-empty\""}},"2.5.1":{"name":"csstype","dist":{"tarball":"https://registry.npmjs.org/csstype/-/csstype-2.5.1.tgz"},"scripts":{"lazy":"tsc && npm run lint && npm run pretty","lint":"tslint --exclude node_modules/**/* --exclude **/*.d.ts --fix **/*.ts","test":"jest --no-cache","build":"ts-node build.ts --start","watch":"ts-node build.ts --watch","pretty":"prettier --write build.ts **/*.{ts,js,json}","update":"ts-node update.ts","typecheck":"tsc typecheck.ts --noEmit --pretty & flow check typecheck.js","prepublish":"tsc && npm run test && npm run build && npm run typecheck","rebase-build":"git rebase --exec \"yarn --ignore-scripts && yarn build && git commit -a --amend --no-verify --no-edit --allow-empty\""}},"2.5.2":{"name":"csstype","dist":{"tarball":"https://registry.npmjs.org/csstype/-/csstype-2.5.2.tgz"},"scripts":{"lazy":"tsc && npm run lint && npm run pretty","lint":"tslint --exclude node_modules/**/* --exclude **/*.d.ts --fix **/*.ts","test":"jest --no-cache","build":"ts-node build.ts --start","watch":"ts-node build.ts --watch","pretty":"prettier --write build.ts **/*.{ts,js,json}","update":"ts-node update.ts","typecheck":"tsc typecheck.ts --noEmit --pretty & flow check typecheck.js","prepublish":"tsc && npm run test && npm run build && npm run typecheck","rebase-build":"git rebase --exec \"yarn --ignore-scripts && yarn build && git commit -a --amend --no-verify --no-edit --allow-empty\""}},"2.5.3":{"name":"csstype","dist":{"tarball":"https://registry.npmjs.org/csstype/-/csstype-2.5.3.tgz"},"scripts":{"lazy":"tsc && npm run lint && npm run pretty","lint":"tslint --exclude node_modules/**/* --exclude **/*.d.ts --fix **/*.ts","test":"jest --no-cache","build":"ts-node build.ts --start","watch":"ts-node build.ts --watch","pretty":"prettier --write build.ts **/*.{ts,js,json}","update":"ts-node update.ts","typecheck":"tsc typecheck.ts --noEmit --pretty & flow check typecheck.js","prepublish":"tsc && npm run test && npm run build && npm run typecheck","rebase-build":"git rebase --exec \"yarn --ignore-scripts && yarn build && git commit -a --amend --no-verify --no-edit --allow-empty\""}},"2.5.4":{"name":"csstype","dist":{"tarball":"https://registry.npmjs.org/csstype/-/csstype-2.5.4.tgz"},"scripts":{"lazy":"tsc && npm run lint && npm run pretty","lint":"tslint --exclude node_modules/**/* --exclude **/*.d.ts --fix **/*.ts","test":"jest --no-cache","build":"ts-node build.ts --start","watch":"ts-node build.ts --watch","pretty":"prettier --write build.ts **/*.{ts,js,json}","update":"ts-node update.ts","typecheck":"tsc typecheck.ts --noEmit --pretty & flow check typecheck.js","prepublish":"tsc && npm run test && npm run build && npm run typecheck","rebase-build":"git rebase --exec \"yarn --ignore-scripts && yarn build && git commit -a --amend --no-verify --no-edit --allow-empty\""}},"2.5.5":{"name":"csstype","dist":{"tarball":"https://registry.npmjs.org/csstype/-/csstype-2.5.5.tgz"},"scripts":{"lazy":"tsc && npm run lint && npm run pretty","lint":"tslint --exclude node_modules/**/* --exclude **/*.d.ts --fix **/*.ts","test":"jest --no-cache","build":"ts-node build.ts --start","watch":"ts-node build.ts --watch","pretty":"prettier --write build.ts **/*.{ts,js,json}","update":"ts-node update.ts","typecheck":"tsc typecheck.ts --noEmit --pretty & flow check typecheck.js","prepublish":"tsc && npm run test && npm run build && npm run typecheck","rebase-build":"git rebase --exec \"yarn --ignore-scripts && yarn build && git commit -a --amend --no-verify --no-edit --allow-empty\""}},"2.5.6":{"name":"csstype","dist":{"tarball":"https://registry.npmjs.org/csstype/-/csstype-2.5.6.tgz"},"scripts":{"lazy":"tsc && npm run lint && npm run pretty","lint":"tslint --exclude node_modules/**/* --exclude **/*.d.ts --fix **/*.ts","test":"jest --no-cache","build":"ts-node build.ts --start","watch":"ts-node build.ts --watch","pretty":"prettier --write build.ts **/*.{ts,js,json}","update":"ts-node update.ts","typecheck":"tsc typecheck.ts --noEmit --pretty & flow check typecheck.js","prepublish":"tsc && npm run test && npm run build && npm run typecheck","rebase-build":"git rebase --exec \"yarn --ignore-scripts && yarn build && git commit -a --amend --no-verify --no-edit --allow-empty\""}},"2.5.7":{"name":"csstype","dist":{"tarball":"https://registry.npmjs.org/csstype/-/csstype-2.5.7.tgz"},"scripts":{"lazy":"tsc && npm run lint && npm run pretty","lint":"tslint --exclude node_modules/**/* --exclude **/*.d.ts --fix **/*.ts","test":"jest --no-cache","build":"ts-node --files build.ts --start","watch":"ts-node --files build.ts --watch","pretty":"prettier --write build.ts **/*.{ts,js,json,md}","update":"ts-node --files update.ts","typecheck":"tsc typecheck.ts --noEmit --pretty & flow check typecheck.js","prepublish":"tsc && npm run test && npm run build && npm run typecheck","rebase-build":"git rebase --exec \"yarn --ignore-scripts && yarn build && git commit -a --amend --no-verify --no-edit --allow-empty\""}},"2.5.8":{"name":"csstype","dist":{"tarball":"https://registry.npmjs.org/csstype/-/csstype-2.5.8.tgz"},"scripts":{"lazy":"tsc && npm run lint && npm run pretty","lint":"tslint --exclude node_modules/**/* --exclude **/*.d.ts --fix **/*.ts","test":"jest --no-cache","build":"ts-node --files build.ts --start","watch":"ts-node --files build.ts --watch","pretty":"prettier --write build.ts **/*.{ts,js,json,md}","update":"ts-node --files update.ts","typecheck":"tsc typecheck.ts --noEmit --pretty & flow check typecheck.js","prepublish":"tsc && npm run test && npm run build && npm run typecheck","rebase-build":"git rebase --exec \"yarn --ignore-scripts && yarn build && git commit -a --amend --no-verify --no-edit --allow-empty\""}},"2.6.0":{"name":"csstype","dist":{"tarball":"https://registry.npmjs.org/csstype/-/csstype-2.6.0.tgz"},"scripts":{"lazy":"tsc && npm run lint && npm run pretty","lint":"tslint --exclude node_modules/**/* --exclude **/*.d.ts --fix **/*.ts","test":"jest --no-cache","build":"ts-node --files build.ts --start","watch":"ts-node --files build.ts --watch","pretty":"prettier --write build.ts **/*.{ts,js,json,md}","update":"ts-node --files update.ts","typecheck":"tsc typecheck.ts --noEmit --pretty & flow check typecheck.js","prepublish":"tsc && npm run test && npm run build && npm run typecheck","rebase-build":"git rebase --exec \"yarn --ignore-scripts && yarn build && git commit -a --amend --no-verify --no-edit --allow-empty\""}},"2.6.1":{"name":"csstype","dist":{"tarball":"https://registry.npmjs.org/csstype/-/csstype-2.6.1.tgz"},"scripts":{"lazy":"tsc && npm run lint && npm run pretty","lint":"tslint --exclude node_modules/**/* --exclude **/*.d.ts --fix **/*.ts","test":"jest --no-cache","build":"ts-node --files build.ts --start","watch":"ts-node --files build.ts --watch","pretty":"prettier --write build.ts **/*.{ts,js,json,md}","update":"ts-node --files update.ts","typecheck":"tsc typecheck.ts --noEmit --pretty & flow check typecheck.js","prepublish":"tsc && npm run test && npm run build && npm run typecheck","rebase-build":"git rebase --exec \"yarn --ignore-scripts && yarn build && git commit -a --amend --no-verify --no-edit --allow-empty\""}},"2.6.2":{"name":"csstype","dist":{"tarball":"https://registry.npmjs.org/csstype/-/csstype-2.6.2.tgz"},"scripts":{"lazy":"tsc && npm run lint && npm run pretty","lint":"tslint --exclude node_modules/**/* --exclude **/*.d.ts --fix **/*.ts","test":"jest --no-cache","build":"ts-node --files build.ts --start","watch":"ts-node --files build.ts --watch","pretty":"prettier --write build.ts **/*.{ts,js,json,md}","update":"ts-node --files update.ts","typecheck":"tsc typecheck.ts --noEmit --pretty & flow check typecheck.js","prepublish":"tsc && npm run test && npm run build && npm run typecheck","rebase-build":"git rebase --exec \"yarn --ignore-scripts && yarn build && git commit -a --amend --no-verify --no-edit --allow-empty\""}},"2.6.3":{"name":"csstype","dist":{"tarball":"https://registry.npmjs.org/csstype/-/csstype-2.6.3.tgz"},"scripts":{"lazy":"tsc && npm run lint && npm run pretty","lint":"tslint --exclude node_modules/**/* --exclude **/*.d.ts --fix **/*.ts","test":"jest --no-cache","build":"ts-node --files build.ts --start","watch":"ts-node --files build.ts --watch","pretty":"prettier --write build.ts **/*.{ts,js,json,md}","update":"ts-node --files update.ts","typecheck":"tsc typecheck.ts --noEmit --pretty & flow check typecheck.js","prepublish":"tsc && npm run test && npm run build && npm run typecheck","rebase-build":"git rebase --exec \"yarn --ignore-scripts && yarn build && git commit -a --amend --no-verify --no-edit --allow-empty\""}},"2.6.4":{"name":"csstype","dist":{"tarball":"https://registry.npmjs.org/csstype/-/csstype-2.6.4.tgz"},"scripts":{"lazy":"tsc && npm run lint && npm run pretty","lint":"tslint --exclude node_modules/**/* --exclude **/*.d.ts --fix **/*.ts","test":"jest --no-cache","build":"ts-node --files build.ts --start","watch":"ts-node --files build.ts --watch","pretty":"prettier --write build.ts **/*.{ts,js,json,md}","update":"ts-node --files update.ts","typecheck":"tsc typecheck.ts --noEmit --pretty & flow check typecheck.js","prepublish":"tsc && npm run test && npm run build && npm run typecheck","rebase-build":"git rebase --exec \"yarn --ignore-scripts && yarn build && git commit -a --amend --no-verify --no-edit --allow-empty\""}},"2.6.5":{"name":"csstype","dist":{"tarball":"https://registry.npmjs.org/csstype/-/csstype-2.6.5.tgz"},"scripts":{"lazy":"tsc && npm run lint && npm run pretty","lint":"tslint --exclude node_modules/**/* --exclude **/*.d.ts --fix **/*.ts","test":"jest --no-cache","build":"ts-node --files build.ts --start","watch":"ts-node --files build.ts --watch","pretty":"prettier --write build.ts **/*.{ts,js,json,md}","update":"ts-node --files update.ts","typecheck":"tsc typecheck.ts --noEmit --pretty & flow check typecheck.js","prepublish":"tsc && npm run test && npm run build && npm run typecheck","rebase-build":"git rebase --exec \"yarn --ignore-scripts && yarn build && git commit -a --amend --no-verify --no-edit --allow-empty\""}},"2.6.6":{"name":"csstype","dist":{"tarball":"https://registry.npmjs.org/csstype/-/csstype-2.6.6.tgz"},"scripts":{"lazy":"tsc && npm run lint && npm run pretty","lint":"tslint --exclude node_modules/**/* --exclude **/*.d.ts --fix **/*.ts","test":"jest --no-cache","build":"ts-node --files build.ts --start","watch":"ts-node --files build.ts --watch","pretty":"prettier --write build.ts **/*.{ts,js,json,md}","update":"ts-node --files update.ts","typecheck":"tsc typecheck.ts --noEmit --pretty & flow check typecheck.js","prepublish":"tsc && npm run test && npm run build && npm run typecheck","rebase-build":"git rebase --exec \"yarn --ignore-scripts && yarn build && git commit -a --amend --no-verify --no-edit --allow-empty\""}},"2.6.7":{"name":"csstype","dist":{"tarball":"https://registry.npmjs.org/csstype/-/csstype-2.6.7.tgz"},"scripts":{"lazy":"tsc && npm run lint && npm run pretty","lint":"tslint --exclude node_modules/**/* --exclude **/*.d.ts --fix **/*.ts","test":"jest --no-cache","build":"ts-node --files build.ts --start","watch":"ts-node --files build.ts --watch","pretty":"prettier --write build.ts **/*.{ts,js,json,md}","update":"ts-node --files update.ts","typecheck":"tsc typecheck.ts --noEmit --pretty & flow check typecheck.js","prepublish":"tsc && npm run test && npm run build && npm run typecheck","rebase-build":"git rebase --exec \"yarn --ignore-scripts && yarn build && git commit -a --amend --no-verify --no-edit --allow-empty\""}},"3.0.0-alpha.0":{"name":"csstype","dist":{"tarball":"https://registry.npmjs.org/csstype/-/csstype-3.0.0-alpha.0.tgz"},"scripts":{"lazy":"tsc && npm run lint && npm run pretty","lint":"tslint --exclude node_modules/**/* --exclude **/*.d.ts --fix **/*.ts","test":"jest --no-cache","build":"ts-node --files build.ts --start","watch":"ts-node --files build.ts --watch","pretty":"prettier --write build.ts **/*.{ts,js,json,md}","update":"ts-node --files update.ts","test-src":"jest src.*.ts --no-cache","test-dist":"jest dist.*.ts --no-cache","prepublish":"tsc && npm run test-src && npm run build","rebase-build":"git rebase --exec \"yarn --ignore-scripts && yarn build && git commit -a --amend --no-verify --no-edit --allow-empty\""}},"3.0.0-alpha.1":{"name":"csstype","dist":{"tarball":"https://registry.npmjs.org/csstype/-/csstype-3.0.0-alpha.1.tgz"},"scripts":{"lazy":"tsc && npm run lint && npm run pretty","lint":"tslint --exclude node_modules/**/* --exclude **/*.d.ts --fix **/*.ts","test":"jest","build":"ts-node --files build.ts --start","watch":"ts-node --files build.ts --watch","pretty":"prettier --write build.ts **/*.{ts,js,json,md}","update":"ts-node --files update.ts","test:src":"jest src.*.ts","test:dist":"jest dist.*.ts","prepublish":"tsc && npm run test:src && npm run build"}},"3.0.0-alpha.2":{"name":"csstype","dist":{"tarball":"https://registry.npmjs.org/csstype/-/csstype-3.0.0-alpha.2.tgz"},"scripts":{"lazy":"tsc && npm run lint && npm run pretty","lint":"tslint --exclude node_modules/**/* --exclude **/*.d.ts --fix **/*.ts","test":"jest","build":"ts-node --files build.ts --start","watch":"ts-node --files build.ts --watch","pretty":"prettier --write build.ts **/*.{ts,js,json,md}","update":"ts-node --files update.ts","test:src":"jest src.*.ts","test:dist":"jest dist.*.ts","prepublish":"tsc && npm run test:src && npm run build"}},"3.0.0-beta.0":{"name":"csstype","dist":{"tarball":"https://registry.npmjs.org/csstype/-/csstype-3.0.0-beta.0.tgz"},"scripts":{"lazy":"tsc && npm run lint && npm run pretty","lint":"tslint --exclude node_modules/**/* --exclude **/*.d.ts --fix **/*.ts","test":"jest","build":"ts-node --files build.ts --start","watch":"ts-node --files build.ts --watch","pretty":"prettier --write build.ts **/*.{ts,js,json,md}","update":"ts-node --files update.ts","test:src":"jest src.*.ts","test:dist":"jest dist.*.ts","prepublish":"tsc && npm run test:src && npm run build"}},"3.0.0-beta.1":{"name":"csstype","dist":{"tarball":"https://registry.npmjs.org/csstype/-/csstype-3.0.0-beta.1.tgz"},"scripts":{"lazy":"tsc && npm run lint && npm run pretty","lint":"tslint --exclude node_modules/**/* --exclude **/*.d.ts --fix **/*.ts","test":"jest","build":"ts-node --files build.ts --start","watch":"ts-node --files build.ts --watch","pretty":"prettier --write build.ts **/*.{ts,js,json,md}","update":"ts-node --files update.ts","test:src":"jest src.*.ts","test:dist":"jest dist.*.ts","prepublish":"tsc && npm run test:src && npm run build"}},"2.6.8":{"name":"csstype","dist":{"tarball":"https://registry.npmjs.org/csstype/-/csstype-2.6.8.tgz"},"scripts":{"lazy":"tsc && npm run lint && npm run pretty","lint":"tslint --exclude node_modules/**/* --exclude **/*.d.ts --fix **/*.ts","test":"jest --no-cache","build":"ts-node --files build.ts --start","watch":"ts-node --files build.ts --watch","pretty":"prettier --write build.ts **/*.{ts,js,json,md}","update":"ts-node --files update.ts","typecheck":"tsc typecheck.ts --noEmit --pretty & flow check typecheck.js","prepublish":"tsc && npm run test && npm run build && npm run typecheck","rebase-build":"git rebase --exec \"yarn --ignore-scripts && yarn build && git commit -a --amend --no-verify --no-edit --allow-empty\""}},"2.6.9":{"name":"csstype","dist":{"tarball":"https://registry.npmjs.org/csstype/-/csstype-2.6.9.tgz"},"scripts":{"lazy":"tsc && npm run lint && npm run pretty","lint":"tslint --exclude node_modules/**/* --exclude **/*.d.ts --fix **/*.ts","test":"jest --no-cache","build":"ts-node --files build.ts --start","watch":"ts-node --files build.ts --watch","pretty":"prettier --write build.ts **/*.{ts,js,json,md}","update":"ts-node --files update.ts","typecheck":"tsc typecheck.ts --noEmit --pretty & flow check typecheck.js","prepublish":"tsc && npm run test && npm run build && npm run typecheck","rebase-build":"git rebase --exec \"yarn --ignore-scripts && yarn build && git commit -a --amend --no-verify --no-edit --allow-empty\""}},"2.6.10":{"name":"csstype","dist":{"tarball":"https://registry.npmjs.org/csstype/-/csstype-2.6.10.tgz"},"scripts":{"lazy":"tsc && npm run lint && npm run pretty","lint":"tslint --exclude node_modules/**/* --exclude **/*.d.ts --fix **/*.ts","test":"jest --no-cache","build":"ts-node --files build.ts --start","watch":"ts-node --files build.ts --watch","pretty":"prettier --write build.ts **/*.{ts,js,json,md}","update":"ts-node --files update.ts","typecheck":"tsc typecheck.ts --noEmit --pretty & flow check typecheck.js","prepublish":"tsc && npm run test && npm run build && npm run typecheck","rebase-build":"git rebase --exec \"yarn --ignore-scripts && yarn build && git commit -a --amend --no-verify --no-edit --allow-empty\""}},"3.0.0-beta.2":{"name":"csstype","dist":{"tarball":"https://registry.npmjs.org/csstype/-/csstype-3.0.0-beta.2.tgz"},"scripts":{"lazy":"tsc && npm run lint && npm run pretty","lint":"tslint --exclude node_modules/**/* --exclude **/*.d.ts --fix **/*.ts","test":"jest","build":"ts-node --files build.ts --start","watch":"ts-node --files build.ts --watch","pretty":"prettier --write build.ts **/*.{ts,js,json,md}","update":"ts-node --files update.ts","install":"yarn install --cwd __tests__","test:src":"jest src.*.ts","test:dist":"jest dist.*.ts","prepublishOnly":"tsc && npm run test:src && npm run build && ts-node --files prepublish.ts"}},"3.0.0-beta.3":{"name":"csstype","dist":{"tarball":"https://registry.npmjs.org/csstype/-/csstype-3.0.0-beta.3.tgz"},"scripts":{"lazy":"tsc && npm run lint && npm run pretty","lint":"tslint --exclude node_modules/**/* --exclude **/*.d.ts --fix **/*.ts","test":"jest","build":"ts-node --files build.ts --start","watch":"ts-node --files build.ts --watch","pretty":"prettier --write build.ts **/*.{ts,js,json,md}","update":"ts-node --files update.ts","test:src":"jest src.*.ts","test:dist":"jest dist.*.ts","prepublish":"yarn install --cwd __tests__","prepublishOnly":"tsc && npm run test:src && npm run build && ts-node --files prepublish.ts"}},"2.6.11":{"name":"csstype","dist":{"tarball":"https://registry.npmjs.org/csstype/-/csstype-2.6.11.tgz"},"scripts":{"lazy":"tsc && npm run lint && npm run pretty","lint":"tslint --exclude node_modules/**/* --exclude **/*.d.ts --fix **/*.ts","test":"jest --no-cache","build":"ts-node --files build.ts --start","watch":"ts-node --files build.ts --watch","pretty":"prettier --write build.ts **/*.{ts,js,json,md}","update":"ts-node --files update.ts","typecheck":"tsc typecheck.ts --noEmit --pretty & flow check typecheck.js","prepublish":"tsc && npm run test && npm run build && npm run typecheck","rebase-build":"git rebase --exec \"yarn --ignore-scripts && yarn build && git commit -a --amend --no-verify --no-edit --allow-empty\""}},"3.0.0-beta.4":{"name":"csstype","dist":{"tarball":"https://registry.npmjs.org/csstype/-/csstype-3.0.0-beta.4.tgz"},"scripts":{"lazy":"tsc && npm run lint && npm run pretty","lint":"tslint --exclude node_modules/**/* --exclude **/*.d.ts --fix **/*.ts","test":"jest","build":"ts-node --files build.ts --start","watch":"ts-node --files build.ts --watch","pretty":"prettier --write build.ts **/*.{ts,js,json,md}","update":"ts-node --files update.ts","test:src":"jest src.*.ts","test:dist":"jest dist.*.ts","prepublish":"yarn install --cwd __tests__","prepublishOnly":"tsc && npm run test:src && npm run build && ts-node --files prepublish.ts"}},"2.6.12":{"name":"csstype","dist":{"tarball":"https://registry.npmjs.org/csstype/-/csstype-2.6.12.tgz"},"scripts":{"lazy":"tsc && npm run lint && npm run pretty","lint":"tslint --exclude node_modules/**/* --exclude **/*.d.ts --fix **/*.ts","test":"jest --no-cache","build":"ts-node --files build.ts --start","watch":"ts-node --files build.ts --watch","pretty":"prettier --write build.ts **/*.{ts,js,json,md}","update":"ts-node --files update.ts","typecheck":"tsc typecheck.ts --noEmit --pretty & flow check typecheck.js","prepublish":"tsc && npm run test && npm run build && npm run typecheck","rebase-build":"git rebase --exec \"yarn --ignore-scripts && yarn build && git commit -a --amend --no-verify --no-edit --allow-empty\""}},"3.0.0":{"name":"csstype","dist":{"tarball":"https://registry.npmjs.org/csstype/-/csstype-3.0.0.tgz"},"scripts":{"lazy":"tsc && npm run lint && npm run pretty","lint":"tslint --exclude node_modules/**/* --exclude **/*.d.ts --fix **/*.ts","test":"jest","build":"ts-node --files build.ts --start","watch":"ts-node --files build.ts --watch","pretty":"prettier --write build.ts **/*.{ts,js,json,md}","update":"ts-node --files update.ts","test:src":"jest src.*.ts","test:dist":"jest dist.*.ts","prepublish":"yarn install --cwd __tests__","prepublishOnly":"tsc && npm run test:src && npm run build && ts-node --files prepublish.ts"}},"2.6.13":{"name":"csstype","dist":{"tarball":"https://registry.npmjs.org/csstype/-/csstype-2.6.13.tgz"},"scripts":{"lazy":"tsc && npm run lint && npm run pretty","lint":"tslint --exclude node_modules/**/* --exclude **/*.d.ts --fix **/*.ts","test":"jest --no-cache","build":"ts-node --files build.ts --start","watch":"ts-node --files build.ts --watch","pretty":"prettier --write build.ts **/*.{ts,js,json,md}","update":"ts-node --files update.ts","typecheck":"tsc typecheck.ts --noEmit --pretty & flow check typecheck.js","prepublish":"tsc && npm run test && npm run build && npm run typecheck","rebase-build":"git rebase --exec \"yarn --ignore-scripts && yarn build && git commit -a --amend --no-verify --no-edit --allow-empty\""}},"3.0.1":{"name":"csstype","dist":{"tarball":"https://registry.npmjs.org/csstype/-/csstype-3.0.1.tgz"},"scripts":{"lazy":"tsc && npm run lint && npm run pretty","lint":"tslint --exclude node_modules/**/* --exclude **/*.d.ts --fix **/*.ts","test":"jest","build":"ts-node --files build.ts --start","watch":"ts-node --files build.ts --watch","pretty":"prettier --write build.ts **/*.{ts,js,json,md}","update":"ts-node --files update.ts","test:src":"jest src.*.ts","test:dist":"jest dist.*.ts","prepublish":"yarn install --cwd __tests__","prepublishOnly":"tsc && npm run test:src && npm run build && ts-node --files prepublish.ts"}},"3.0.2":{"name":"csstype","dist":{"tarball":"https://registry.npmjs.org/csstype/-/csstype-3.0.2.tgz"},"scripts":{"lazy":"tsc && npm run lint && npm run pretty","lint":"tslint --exclude node_modules/**/* --exclude **/*.d.ts --fix **/*.ts","test":"jest","build":"ts-node --files build.ts --start","watch":"ts-node --files build.ts --watch","pretty":"prettier --write build.ts **/*.{ts,js,json,md}","update":"ts-node --files update.ts","test:src":"jest src.*.ts","test:dist":"jest dist.*.ts","prepublish":"yarn install --cwd __tests__","prepublishOnly":"tsc && npm run test:src && npm run build && ts-node --files prepublish.ts"}},"3.0.3":{"name":"csstype","dist":{"tarball":"https://registry.npmjs.org/csstype/-/csstype-3.0.3.tgz"},"scripts":{"lazy":"tsc && npm run lint && npm run pretty","lint":"tslint --exclude node_modules/**/* --exclude **/*.d.ts --fix **/*.ts","test":"jest","build":"ts-node --files build.ts --start","watch":"ts-node --files build.ts --watch","pretty":"prettier --write build.ts **/*.{ts,js,json,md}","update":"ts-node --files update.ts","test:src":"jest src.*.ts","test:dist":"jest dist.*.ts","prepublish":"yarn install --cwd __tests__","prepublishOnly":"tsc && npm run test:src && npm run build && ts-node --files prepublish.ts"}},"3.0.4":{"name":"csstype","dist":{"tarball":"https://registry.npmjs.org/csstype/-/csstype-3.0.4.tgz"},"scripts":{"lazy":"tsc && npm run lint && npm run pretty","lint":"tslint --exclude node_modules/**/* --exclude **/*.d.ts --fix **/*.ts","test":"jest","build":"ts-node --files build.ts --start","watch":"ts-node --files build.ts --watch","pretty":"prettier --write build.ts **/*.{ts,js,json,md}","update":"ts-node --files update.ts","test:src":"jest src.*.ts","test:dist":"jest dist.*.ts","prepublish":"yarn install --cwd __tests__","prepublishOnly":"tsc && npm run test:src && npm run build && ts-node --files prepublish.ts"}},"3.0.5":{"name":"csstype","dist":{"tarball":"https://registry.npmjs.org/csstype/-/csstype-3.0.5.tgz"},"scripts":{"lazy":"tsc && npm run lint && npm run pretty","lint":"tslint --exclude node_modules/**/* --exclude **/*.d.ts --fix **/*.ts","test":"jest","build":"ts-node --files build.ts --start","watch":"ts-node --files build.ts --watch","pretty":"prettier --write build.ts **/*.{ts,js,json,md}","update":"ts-node --files update.ts","test:src":"jest src.*.ts","test:dist":"jest dist.*.ts","prepublish":"yarn install --cwd __tests__ && yarn install --cwd __tests__/__fixtures__","prepublishOnly":"tsc && npm run test:src && npm run build && ts-node --files prepublish.ts"}},"2.6.14":{"name":"csstype","dist":{"tarball":"https://registry.npmjs.org/csstype/-/csstype-2.6.14.tgz"},"scripts":{"lazy":"tsc && npm run lint && npm run pretty","lint":"tslint --exclude node_modules/**/* --exclude **/*.d.ts --fix **/*.ts","test":"jest --no-cache","build":"ts-node --files build.ts --start","watch":"ts-node --files build.ts --watch","pretty":"prettier --write build.ts **/*.{ts,js,json,md}","update":"ts-node --files update.ts","typecheck":"tsc typecheck.ts --noEmit --pretty & flow check typecheck.js","prepublish":"tsc && npm run test && npm run build && npm run typecheck","rebase-build":"git rebase --exec \"yarn --ignore-scripts && yarn build && git commit -a --amend --no-verify --no-edit --allow-empty\""}},"3.0.6":{"name":"csstype","dist":{"tarball":"https://registry.npmjs.org/csstype/-/csstype-3.0.6.tgz"},"scripts":{"lazy":"tsc && npm run lint && npm run pretty","lint":"tslint --exclude node_modules/**/* --exclude **/*.d.ts --fix **/*.ts","test":"jest","build":"ts-node --files build.ts --start","watch":"ts-node --files build.ts --watch","pretty":"prettier --write build.ts **/*.{ts,js,json,md}","update":"ts-node --files update.ts","test:src":"jest src.*.ts","test:dist":"jest dist.*.ts","prepublish":"yarn install --cwd __tests__ && yarn install --cwd __tests__/__fixtures__","prepublishOnly":"tsc && npm run test:src && npm run build && ts-node --files prepublish.ts"}},"2.6.15":{"name":"csstype","dist":{"tarball":"https://registry.npmjs.org/csstype/-/csstype-2.6.15.tgz"},"scripts":{"lazy":"tsc && npm run lint && npm run pretty","lint":"tslint --exclude node_modules/**/* --exclude **/*.d.ts --fix **/*.ts","test":"jest --no-cache","build":"ts-node --files build.ts --start","watch":"ts-node --files build.ts --watch","pretty":"prettier --write build.ts **/*.{ts,js,json,md}","update":"ts-node --files update.ts","typecheck":"tsc typecheck.ts --noEmit --pretty & flow check typecheck.js","prepublish":"tsc && npm run test && npm run build && npm run typecheck","rebase-build":"git rebase --exec \"yarn --ignore-scripts && yarn build && git commit -a --amend --no-verify --no-edit --allow-empty\""}},"2.6.16":{"name":"csstype","dist":{"tarball":"https://registry.npmjs.org/csstype/-/csstype-2.6.16.tgz"},"scripts":{"lazy":"tsc && npm run lint && npm run pretty","lint":"tslint --exclude node_modules/**/* --exclude **/*.d.ts --fix **/*.ts","test":"jest --no-cache","build":"ts-node --files build.ts --start","watch":"ts-node --files build.ts --watch","pretty":"prettier --write build.ts **/*.{ts,js,json,md}","update":"ts-node --files update.ts","typecheck":"tsc typecheck.ts --noEmit --pretty & flow check typecheck.js","prepublish":"tsc && npm run test && npm run build && npm run typecheck","rebase-build":"git rebase --exec \"yarn --ignore-scripts && yarn build && git commit -a --amend --no-verify --no-edit --allow-empty\""}},"3.0.7":{"name":"csstype","dist":{"tarball":"https://registry.npmjs.org/csstype/-/csstype-3.0.7.tgz"},"scripts":{"lazy":"tsc && npm run lint && npm run pretty","lint":"tslint --exclude node_modules/**/* --exclude **/*.d.ts --fix **/*.ts","test":"jest","build":"ts-node --files build.ts --start","watch":"ts-node --files build.ts --watch","pretty":"prettier --write build.ts **/*.{ts,js,json,md}","update":"ts-node --files update.ts","test:src":"jest src.*.ts","test:dist":"jest dist.*.ts","prepublish":"yarn install --cwd __tests__ && yarn install --cwd __tests__/__fixtures__","prepublishOnly":"tsc && npm run test:src && npm run build && ts-node --files prepublish.ts"}},"3.0.8":{"name":"csstype","dist":{"tarball":"https://registry.npmjs.org/csstype/-/csstype-3.0.8.tgz"},"scripts":{"lazy":"tsc && npm run lint && npm run pretty","lint":"tslint --exclude node_modules/**/* --exclude **/*.d.ts --fix **/*.ts","test":"jest","build":"ts-node --files build.ts --start","watch":"ts-node --files build.ts --watch","pretty":"prettier --write build.ts **/*.{ts,js,json,md}","update":"ts-node --files update.ts","test:src":"jest src.*.ts","test:dist":"jest dist.*.ts","prepublish":"yarn install --cwd __tests__ && yarn install --cwd __tests__/__fixtures__","prepublishOnly":"tsc && npm run test:src && npm run build && ts-node --files prepublish.ts"}},"2.6.17":{"name":"csstype","dist":{"tarball":"https://registry.npmjs.org/csstype/-/csstype-2.6.17.tgz"},"scripts":{"lazy":"tsc && npm run lint && npm run pretty","lint":"tslint --exclude node_modules/**/* --exclude **/*.d.ts --fix **/*.ts","test":"jest --no-cache","build":"ts-node --files build.ts --start","watch":"ts-node --files build.ts --watch","pretty":"prettier --write build.ts **/*.{ts,js,json,md}","update":"ts-node --files update.ts","typecheck":"tsc typecheck.ts --noEmit --pretty & flow check typecheck.js","prepublish":"tsc && npm run test && npm run build && npm run typecheck","rebase-build":"git rebase --exec \"yarn --ignore-scripts && yarn build && git commit -a --amend --no-verify --no-edit --allow-empty\""}},"2.6.18":{"name":"csstype","dist":{"tarball":"https://registry.npmjs.org/csstype/-/csstype-2.6.18.tgz"},"scripts":{"lazy":"tsc && npm run lint && npm run pretty","lint":"tslint --exclude node_modules/**/* --exclude **/*.d.ts --fix **/*.ts","test":"jest --no-cache","build":"ts-node --files build.ts --start","watch":"ts-node --files build.ts --watch","pretty":"prettier --write build.ts **/*.{ts,js,json,md}","update":"ts-node --files update.ts","typecheck":"tsc typecheck.ts --noEmit --pretty & flow check typecheck.js","prepublish":"tsc && npm run test && npm run build && npm run typecheck","rebase-build":"git rebase --exec \"yarn --ignore-scripts && yarn build && git commit -a --amend --no-verify --no-edit --allow-empty\""}},"3.0.9":{"name":"csstype","dist":{"tarball":"https://registry.npmjs.org/csstype/-/csstype-3.0.9.tgz"},"scripts":{"lazy":"tsc && npm run lint","lint":"eslint . --ext .js,.jsx,.ts,.tsx --fix","test":"jest","build":"ts-node --files build.ts --start","watch":"ts-node --files build.ts --watch","pretty":"prettier --write build.ts **/*.{ts,js,json,md}","update":"ts-node --files update.ts","test:src":"jest src.*.ts","test:dist":"jest dist.*.ts","prepublish":"npm install --prefix __tests__ && npm install --prefix __tests__/__fixtures__","prepublishOnly":"tsc && npm run test:src && npm run build && ts-node --files prepublish.ts"}},"3.0.10":{"name":"csstype","dist":{"tarball":"https://registry.npmjs.org/csstype/-/csstype-3.0.10.tgz"},"scripts":{"lazy":"tsc && npm run lint","lint":"eslint . --ext .js,.jsx,.ts,.tsx --fix","test":"jest","build":"ts-node --files build.ts --start","watch":"ts-node --files build.ts --watch","pretty":"prettier --write build.ts **/*.{ts,js,json,md}","update":"ts-node --files update.ts","test:src":"jest src.*.ts","test:dist":"jest dist.*.ts","prepublish":"npm install --prefix __tests__ && npm install --prefix __tests__/__fixtures__","prepublishOnly":"tsc && npm run test:src && npm run build && ts-node --files prepublish.ts"}},"2.6.19":{"name":"csstype","dist":{"tarball":"https://registry.npmjs.org/csstype/-/csstype-2.6.19.tgz"},"scripts":{"lazy":"tsc && npm run lint && npm run pretty","lint":"tslint --exclude node_modules/**/* --exclude **/*.d.ts --fix **/*.ts","test":"jest --no-cache","build":"ts-node --files build.ts --start","watch":"ts-node --files build.ts --watch","pretty":"prettier --write build.ts **/*.{ts,js,json,md}","update":"ts-node --files update.ts","typecheck":"tsc typecheck.ts --noEmit --pretty & flow check typecheck.js","prepublish":"tsc && npm run test && npm run build && npm run typecheck","rebase-build":"git rebase --exec \"yarn --ignore-scripts && yarn build && git commit -a --amend --no-verify --no-edit --allow-empty\""}},"2.6.20":{"name":"csstype","dist":{"tarball":"https://registry.npmjs.org/csstype/-/csstype-2.6.20.tgz"},"scripts":{"lazy":"tsc && npm run lint && npm run pretty","lint":"tslint --exclude node_modules/**/* --exclude **/*.d.ts --fix **/*.ts","test":"jest --no-cache","build":"ts-node --files build.ts --start","watch":"ts-node --files build.ts --watch","pretty":"prettier --write build.ts **/*.{ts,js,json,md}","update":"ts-node --files update.ts","typecheck":"tsc typecheck.ts --noEmit --pretty & flow check typecheck.js","prepublish":"tsc && npm run test && npm run build && npm run typecheck","rebase-build":"git rebase --exec \"yarn --ignore-scripts && yarn build && git commit -a --amend --no-verify --no-edit --allow-empty\""}},"3.0.11":{"name":"csstype","dist":{"tarball":"https://registry.npmjs.org/csstype/-/csstype-3.0.11.tgz"},"scripts":{"lazy":"tsc && npm run lint","lint":"eslint . --ext .js,.jsx,.ts,.tsx --fix","test":"jest","build":"ts-node --files build.ts --start","watch":"ts-node --files build.ts --watch","pretty":"prettier --write build.ts **/*.{ts,js,json,md}","update":"ts-node --files update.ts","test:src":"jest src.*.ts","test:dist":"jest dist.*.ts","prepublish":"npm install --prefix __tests__ && npm install --prefix __tests__/__fixtures__","prepublishOnly":"tsc && npm run test:src && npm run build && ts-node --files prepublish.ts"}},"3.1.0":{"name":"csstype","dist":{"tarball":"https://registry.npmjs.org/csstype/-/csstype-3.1.0.tgz"},"scripts":{"lazy":"tsc && npm run lint","lint":"eslint . --ext .js,.jsx,.ts,.tsx --fix","test":"jest","build":"ts-node --files build.ts --start","watch":"ts-node --files build.ts --watch","pretty":"prettier --write build.ts **/*.{ts,js,json,md}","update":"ts-node --files update.ts","test:src":"jest src.*.ts","test:dist":"jest dist.*.ts","prepublish":"npm install --prefix __tests__ && npm install --prefix __tests__/__fixtures__","prepublishOnly":"tsc && npm run test:src && npm run build && ts-node --files prepublish.ts"}},"3.1.1":{"name":"csstype","dist":{"tarball":"https://registry.npmjs.org/csstype/-/csstype-3.1.1.tgz"},"scripts":{"lazy":"tsc && npm run lint","lint":"eslint . --ext .js,.jsx,.ts,.tsx --fix","test":"jest","build":"ts-node --files build.ts --start","watch":"ts-node --files build.ts --watch","pretty":"prettier --write build.ts **/*.{ts,js,json,md}","update":"ts-node --files update.ts","test:src":"jest src.*.ts","test:dist":"jest dist.*.ts","prepublish":"npm install --prefix __tests__ && npm install --prefix __tests__/__fixtures__","prepublishOnly":"tsc && npm run test:src && npm run build && ts-node --files prepublish.ts"}},"2.6.21":{"name":"csstype","dist":{"tarball":"https://registry.npmjs.org/csstype/-/csstype-2.6.21.tgz"},"scripts":{"lazy":"tsc && npm run lint && npm run pretty","lint":"tslint --exclude node_modules/**/* --exclude **/*.d.ts --fix **/*.ts","test":"jest --no-cache","build":"ts-node --files build.ts --start","watch":"ts-node --files build.ts --watch","pretty":"prettier --write build.ts **/*.{ts,js,json,md}","update":"ts-node --files update.ts","typecheck":"tsc typecheck.ts --noEmit --pretty & flow check typecheck.js","prepublish":"tsc && npm run test && npm run build && npm run typecheck"}},"3.1.2":{"name":"csstype","dist":{"tarball":"https://registry.npmjs.org/csstype/-/csstype-3.1.2.tgz"},"scripts":{"lazy":"tsc && npm run lint","lint":"eslint . --ext .js,.jsx,.ts,.tsx --fix","test":"jest --runInBand","build":"ts-node --files build.ts --start","watch":"ts-node --files build.ts --watch","pretty":"prettier --write build.ts **/*.{ts,js,json,md}","update":"ts-node --files update.ts","test:src":"jest src.*.ts","test:dist":"jest dist.*.ts --runInBand","prepublish":"npm install --prefix __tests__ && npm install --prefix __tests__/__fixtures__","prepublishOnly":"tsc && npm run test:src && npm run build && ts-node --files prepublish.ts"}},"3.1.3":{"name":"csstype","dist":{"tarball":"https://registry.npmjs.org/csstype/-/csstype-3.1.3.tgz"},"scripts":{"lazy":"tsc && npm run lint","lint":"eslint . --ext .js,.jsx,.ts,.tsx --fix","test":"jest --runInBand","build":"ts-node --files build.ts --start","watch":"ts-node --files build.ts --watch","pretty":"prettier --write build.ts **/*.{ts,js,json,md}","update":"ts-node --files update.ts","test:src":"jest src.*.ts","test:dist":"jest dist.*.ts --runInBand","prepublish":"npm install --prefix __tests__ && npm install --prefix __tests__/__fixtures__","prepublishOnly":"tsc && npm run test:src && npm run build && ts-node --files prepublish.ts"}},"3.2.0":{"name":"csstype","dist":{"tarball":"https://registry.npmjs.org/csstype/-/csstype-3.2.0.tgz"},"scripts":{"lazy":"tsc && npm run lint","lint":"eslint . --ext .js,.jsx,.ts,.tsx --fix","test":"jest --runInBand","build":"tsx --inspect build.ts --start","watch":"tsx build.ts --watch","pretty":"prettier --write build.ts **/*.{ts,js,json,md}","update":"tsx update.ts","test:src":"jest src.*.ts","test:dist":"jest dist.*.ts --runInBand","prepublish":"npm install --prefix __tests__ && npm install --prefix __tests__/__fixtures__","prepublishOnly":"tsc && npm run test:src && npm run build && tsx prepublish.ts"}},"3.2.1":{"name":"csstype","dist":{"tarball":"https://registry.npmjs.org/csstype/-/csstype-3.2.1.tgz"},"scripts":{"lazy":"tsc && npm run lint","lint":"eslint . --ext .js,.jsx,.ts,.tsx --fix","test":"jest --runInBand","build":"tsx --inspect build.ts --start","watch":"tsx build.ts --watch","pretty":"prettier --write build.ts **/*.{ts,js,json,md}","update":"tsx update.ts","test:src":"jest src.*.ts","test:dist":"jest dist.*.ts --runInBand","prepublish":"npm install --prefix __tests__ && npm install --prefix __tests__/__fixtures__","prepublishOnly":"tsc && npm run test:src && npm run build && tsx prepublish.ts"}},"3.2.2":{"name":"csstype","dist":{"tarball":"https://registry.npmjs.org/csstype/-/csstype-3.2.2.tgz"},"scripts":{"lazy":"tsc && npm run lint","lint":"eslint . --ext .js,.jsx,.ts,.tsx --fix","test":"jest --runInBand","build":"tsx --inspect build.ts --start","watch":"tsx build.ts --watch","pretty":"prettier --write build.ts **/*.{ts,js,json,md}","update":"tsx update.ts","release":"release-it","test:src":"jest src.*.ts","test:dist":"jest dist.*.ts --runInBand","prepublish":"npm install --prefix __tests__ && npm install --prefix __tests__/__fixtures__"}},"3.2.3":{"name":"csstype","dist":{"tarball":"https://registry.npmjs.org/csstype/-/csstype-3.2.3.tgz"},"scripts":{"prepublish":"npm install --no-save --prefix __tests__ && npm install --no-save --prefix __tests__/__fixtures__","release":"release-it","update":"tsx update.ts","build":"tsx --inspect build.ts --start","watch":"tsx build.ts --watch","lint":"eslint . --ext .js,.jsx,.ts,.tsx --fix","pretty":"prettier --write build.ts **/*.{ts,js,json,md}","lazy":"tsc && npm run lint","test":"jest --runInBand","test:src":"jest src.*.ts","test:dist":"jest dist.*.ts --runInBand"}}},"time":{"created":"2017-09-24T22:14:25.900Z","modified":"2025-11-17T11:42:27.229Z","1.0.0":"2017-09-24T22:14:25.900Z","1.0.1":"2017-09-25T18:50:47.848Z","1.1.0":"2017-09-25T22:36:58.659Z","1.2.0":"2018-01-15T16:36:23.346Z","1.2.1":"2018-01-15T21:31:19.227Z","1.3.0":"2018-01-18T08:14:23.007Z","1.4.0":"2018-02-03T00:23:05.971Z","1.5.0":"2018-02-07T20:51:55.931Z","1.6.0":"2018-02-12T14:50:05.920Z","1.7.0":"2018-02-13T22:32:53.327Z","1.7.1":"2018-02-15T14:03:40.090Z","1.7.2":"2018-02-19T07:18:36.997Z","1.8.0":"2018-02-22T10:08:04.873Z","1.8.1":"2018-03-01T12:45:01.240Z","1.8.2":"2018-03-02T22:59:41.357Z","2.0.0":"2018-03-19T09:23:50.404Z","2.1.0":"2018-04-04T18:26:32.502Z","2.1.1":"2018-04-05T07:09:01.050Z","2.2.0":"2018-04-11T07:48:41.012Z","2.3.0":"2018-04-18T22:27:52.004Z","2.3.1":"2018-04-24T07:02:46.073Z","2.4.0":"2018-04-24T19:10:35.271Z","2.4.1":"2018-04-26T08:12:11.967Z","2.4.2":"2018-04-28T07:40:36.879Z","2.5.0":"2018-05-09T21:52:08.425Z","2.5.1":"2018-05-11T23:08:46.112Z","2.5.2":"2018-05-16T22:15:49.595Z","2.5.3":"2018-05-29T12:28:22.761Z","2.5.4":"2018-06-18T22:01:18.298Z","2.5.5":"2018-06-19T18:56:13.207Z","2.5.6":"2018-07-21T22:49:25.449Z","2.5.7":"2018-09-13T07:03:14.369Z","2.5.8":"2018-12-03T07:59:16.234Z","2.6.0":"2018-12-27T10:21:18.799Z","2.6.1":"2019-01-18T08:24:08.156Z","2.6.2":"2019-01-29T20:46:08.213Z","2.6.3":"2019-03-05T12:04:42.724Z","2.6.4":"2019-04-17T11:18:59.647Z","2.6.5":"2019-05-27T13:23:48.618Z","2.6.6":"2019-07-08T09:47:22.841Z","2.6.7":"2019-10-04T18:43:46.270Z","3.0.0-alpha.0":"2019-11-16T19:12:27.226Z","3.0.0-alpha.1":"2019-11-22T19:11:14.279Z","3.0.0-alpha.2":"2019-11-22T20:18:48.155Z","3.0.0-beta.0":"2019-12-01T19:34:45.590Z","3.0.0-beta.1":"2019-12-04T14:15:50.715Z","2.6.8":"2019-12-16T07:13:39.867Z","2.6.9":"2020-02-14T06:23:42.007Z","2.6.10":"2020-03-30T07:39:06.273Z","3.0.0-beta.2":"2020-03-30T07:52:18.356Z","3.0.0-beta.3":"2020-04-15T07:23:13.382Z","2.6.11":"2020-07-01T10:55:14.670Z","3.0.0-beta.4":"2020-07-01T11:02:31.902Z","2.6.12":"2020-07-29T18:43:26.352Z","3.0.0":"2020-07-29T18:48:04.859Z","2.6.13":"2020-07-29T19:46:52.454Z","3.0.1":"2020-07-29T19:54:48.798Z","3.0.2":"2020-07-30T10:01:51.820Z","3.0.3":"2020-08-25T10:05:46.976Z","3.0.4":"2020-10-23T07:58:46.941Z","3.0.5":"2020-11-13T08:52:43.932Z","2.6.14":"2020-11-13T08:56:34.242Z","3.0.6":"2021-01-08T12:29:00.640Z","2.6.15":"2021-02-16T09:17:23.138Z","2.6.16":"2021-02-24T09:31:35.839Z","3.0.7":"2021-02-24T09:40:44.118Z","3.0.8":"2021-04-19T07:35:09.726Z","2.6.17":"2021-04-19T07:46:17.945Z","2.6.18":"2021-09-13T13:39:25.643Z","3.0.9":"2021-09-13T13:42:44.181Z","3.0.10":"2021-11-15T11:06:12.378Z","2.6.19":"2021-11-18T08:30:47.806Z","2.6.20":"2022-03-03T14:07:56.563Z","3.0.11":"2022-03-03T14:13:37.056Z","3.1.0":"2022-05-16T13:23:39.563Z","3.1.1":"2022-09-13T07:46:39.111Z","2.6.21":"2022-09-14T08:51:14.521Z","3.1.2":"2023-04-01T20:49:15.271Z","3.1.3":"2023-12-07T10:18:21.772Z","3.2.0":"2025-11-14T08:21:10.225Z","3.2.1":"2025-11-15T09:59:37.770Z","3.2.2":"2025-11-16T13:47:56.086Z","3.2.3":"2025-11-17T11:42:27.045Z"}},"etag":"W/\"786b201a8a63fbb9ce05145ca07fc4fe\"","lastModified":"Mon, 17 Nov 2025 11:42:28 GMT"}
